Workbook

Sheet Data
A1: Transaction ID | B1: Item | C1: Quantity | D1: Price Per Unit | E1: Total Spent | F1: Payment Method | G1: Location | H1: Transaction Date
A2: TXN_1961373 | B2: Coffee | C2: 2 | D2: 2 | E2: 4 | F2: Credit Card | G2: Takeaway | H2: 45177
A3: TXN_4977031 | B3: Cake | C3: 4 | D3: 3 | E3: 12 | F3: Cash | G3: In-store | H3: 45062
A4: TXN_4271903 | B4: Cookie | C4: 4 | D4: 1 | E4: 4 | F4: Credit Card | G4: In-store | H4: 45126
A5: TXN_7034554 | B5: Salad | C5: 2 | D5: 5 | E5: 10 | H5: 45043
A6: TXN_3160411 | B6: Coffee | C6: 2 | D6: 2 | E6: 4 | F6: Digital Wallet | G6: In-store | H6: 45088
A7: TXN_2602893 | B7: Smoothie | C7: 5 | D7: 4 | E7: 20 | F7: Credit Card | H7: 45016
A8: TXN_4433211 | C8: 3 | D8: 3 | E8: 9 | G8: Takeaway | H8: 45205
A9: TXN_6699534 | B9: Sandwich | C9: 4 | D9: 4 | E9: 16 | F9: Cash | H9: 45227
A10: TXN_4717867 | C10: 5 | D10: 3 | E10: 15 | G10: Takeaway | H10: 45135
A11: TXN_2064365 | B11: Sandwich | C11: 5 | D11: 4 | E11: 20 | G11: In-store | H11: 45291
A12: TXN_2548360 | B12: Salad | C12: 5 | D12: 5 | E12: 25 | F12: Cash | G12: Takeaway | H12: 45237
A13: TXN_3051279 | B13: Sandwich | C13: 2 | D13: 4 | E13: 8 | F13: Credit Card | G13: Takeaway
A14: TXN_7619095 | B14: Sandwich | C14: 2 | D14: 4 | E14: 8 | F14: Cash | G14: In-store | H14: 45049
A15: TXN_9437049 | B15: Cookie | C15: 5 | D15: 1 | E15: 5 | G15: Takeaway | H15: 45078
A16: TXN_8915701 | C16: 2 | D16: 1.5 | E16: 3 | G16: In-store | H16: 45006
A17: TXN_2847255 | B17: Salad | C17: 3 | D17: 5 | E17: 15 | F17: Credit Card | G17: In-store | H17: 45245
A18: TXN_3765707 | B18: Sandwich | C18: 1 | D18: 4 | E18: 4 | H18: 45087
A19: TXN_6769710 | B19: Juice | C19: 2 | D19: 3 | E19: 6 | F19: Cash | G19: In-store | H19: 44981
A20: TXN_8876618 | B20: Cake | C20: 5 | D20: 3 | E20: 15 | F20: Cash | H20: 45010
A21: TXN_3709394 | B21: Juice | C21: 4 | D21: 3 | E21: 12 | F21: Cash | G21: Takeaway | H21: 44941
A22: TXN_3522028 | B22: Smoothie | C22: 5 | D22: 4 | E22: 20 | F22: Cash | G22: In-store | H22: 45020
A23: TXN_3567645 | B23: Smoothie | C23: 4 | D23: 4 | E23: 16 | F23: Credit Card | G23: Takeaway | H23: 45015
A24: TXN_5132361 | B24: Sandwich | C24: 3 | D24: 4 | E24: 12 | F24: Digital Wallet | G24: Takeaway | H24: 45261
A25: TXN_2616390 | B25: Sandwich | C25: 2 | D25: 4 | E25: 8 | H25: 45187
A26: TXN_9400181 | B26: Sandwich | C26: 5 | D26: 4 | E26: 20 | F26: Cash | G26: In-store | H26: 45080
A27: TXN_7958992 | B27: Smoothie | C27: 3 | D27: 4 | E27: 12 | H27: 45273
A28: TXN_5183041 | B28: Cookie | C28: 5 | D28: 1 | E28: 5 | F28: Credit Card | G28: In-store | H28: 45036
A29: TXN_5695074 | B29: Juice | C29: 4 | D29: 3 | E29: 12 | F29: Credit Card | G29: Takeaway | H29: 45026
A30: TXN_8467949 | B30: Smoothie | C30: 5 | D30: 4 | E30: 20 | F30: Credit Card | H30: 44996
A31: TXN_7640952 | B31: Cake | C31: 4 | D31: 3 | E31: 12 | F31: Digital Wallet | G31: Takeaway
A32: TXN_1736287 | C32: 5 | D32: 2 | E32: 10 | F32: Digital Wallet | H32: 45079
A33: TXN_8927252 | C33: 2 | D33: 1 | E33: 2 | F33: Credit Card | H33: 45236
A34: TXN_9677376 | B34: Smoothie | C34: 4 | D34: 4 | E34: 16 | G34: In-store | H34: 45153
A35: TXN_7710508 | C35: 5 | D35: 1 | E35: 5 | F35: Cash
A36: TXN_8853997 | B36: Smoothie | C36: 2 | D36: 4 | E36: 8 | F36: Digital Wallet | G36: Takeaway | H36: 45208
A37: TXN_9130559 | B37: Sandwich | C37: 1 | D37: 4 | E37: 4 | F37: Credit Card | H37: 45074
A38: TXN_6855453 | C38: 4 | D38: 3 | E38: 12 | G38: In-store | H38: 45124
A39: TXN_1080432 | B39: Salad | C39: 2 | D39: 5 | E39: 10 | F39: Credit Card | G39: In-store | H39: 45045
A40: TXN_2655815 | B40: Smoothie | C40: 4 | D40: 4 | E40: 16 | G40: Takeaway | H40: 45085
A41: TXN_6688524 | B41: Coffee | C41: 4 | D41: 2 | E41: 8 | H41: 45106
A42: TXN_2083138 | B42: Smoothie | C42: 3 | D42: 4 | E42: 12 | G42: In-store | H42: 45033
A43: TXN_2427584 | B43: Sandwich | C43: 4 | D43: 4 | E43: 16 | G43: Takeaway | H43: 45282
A44: TXN_6650263 | B44: Tea | C44: 2 | D44: 1.5 | E44: 3 | G44: Takeaway | H44: 44936
A45: TXN_9620080 | B45: Juice | C45: 4 | D45: 3 | E45: 12 | G45: Takeaway | H45: 45201
A46: TXN_1491578 | B46: Cookie | C46: 2 | D46: 1 | E46: 2 | H46: 44980
A47: TXN_5455792 | B47: Salad | C47: 3 | D47: 5 | E47: 15 | F47: Cash | H47: 45007
A48: TXN_8078640 | B48: Juice | C48: 4 | D48: 3 | E48: 12 | F48: Digital Wallet | G48: In-store | H48: 45233
A49: TXN_9499313 | B49: Juice | C49: 5 | D49: 3 | E49: 15 | H49: 44987
A50: TXN_8201146 | B50: Juice | C50: 5 | D50: 3 | E50: 15 | F50: Cash | H50: 45103
A51: TXN_8230936 | B51: Cake | C51: 3 | D51: 3 | E51: 9 | H51: 45048
A52: TXN_7742742 | B52: Cake | C52: 5 | D52: 3 | E52: 15 | G52: Takeaway | H52: 45174
A53: TXN_6342161 | B53: Salad | C53: 5 | D53: 5 | E53: 25 | G53: Takeaway | H53: 44934
A54: TXN_8914892 | C54: 5 | D54: 5 | E54: 25 | F54: Digital Wallet | H54: 45000
A55: TXN_3363746 | B55: Smoothie | C55: 3 | D55: 4 | E55: 12 | F55: Credit Card | H55: 45255
A56: TXN_8614868 | B56: Smoothie | C56: 5 | D56: 4 | E56: 20 | F56: Digital Wallet | G56: Takeaway | H56: 45265
A57: TXN_5522862 | B57: Cookie | C57: 2 | D57: 1 | E57: 2 | F57: Credit Card | G57: Takeaway | H57: 45004
A58: TXN_3578141 | B58: Cake | C58: 5 | D58: 3 | E58: 15 | G58: Takeaway | H58: 45104
A59: TXN_2080895 | B59: Cake | C59: 1 | D59: 3 | E59: 3 | F59: Digital Wallet | G59: In-store | H59: 45035
A60: TXN_6421134 | B60: Sandwich | C60: 4 | D60: 4 | E60: 16 | F60: Cash | G60: Takeaway | H60: 45233
A61: TXN_8813311 | B61: Juice | C61: 5 | D61: 3 | E61: 15 | G61: In-store | H61: 45206
A62: TXN_9023317 | B62: Salad | C62: 1 | D62: 5 | E62: 5 | H62: 45199
A63: TXN_8051289 | C63: 1 | D63: 3 | E63: 3 | G63: In-store | H63: 45208
A64: TXN_2537617 | B64: Sandwich | C64: 1 | D64: 4 | E64: 4 | F64: Cash | H64: 45073
A65: TXN_9099694 | C65: 3 | D65: 5 | E65: 15 | G65: Takeaway | H65: 45248
A66: TXN_9230615 | B66: Smoothie | C66: 4 | D66: 4 | E66: 16 | F66: Digital Wallet | H66: 45078
A67: TXN_4987129 | B67: Sandwich | C67: 3 | D67: 4 | E67: 12 | G67: In-store | H67: 45219
A68: TXN_8501819 | B68: Juice | C68: 2 | D68: 3 | E68: 6 | F68: Cash | H68: 45015
A69: TXN_3068204 | B69: Cookie | C69: 1 | D69: 1 | E69: 1 | F69: Credit Card | G69: Takeaway | H69: 45202
A70: TXN_8427104 | B70: Salad | C70: 2 | D70: 5 | E70: 10 | G70: In-store | H70: 45226
A71: TXN_8471743 | C71: 5 | D71: 3 | E71: 15 | F71: Digital Wallet | G71: In-store | H71: 45022
A72: TXN_2621580 | B72: Tea | C72: 2 | D72: 1.5 | E72: 3 | F72: Cash | G72: In-store | H72: 45007
A73: TXN_4726376 | B73: Cake | C73: 2 | D73: 3 | E73: 6 | F73: Credit Card | G73: In-store | H73: 44957
A74: TXN_6044979 | C74: 1 | D74: 1 | E74: 1 | F74: Cash | G74: In-store | H74: 45268
A75: TXN_4238417 | B75: Salad | C75: 2 | D75: 5 | E75: 10 | H75: 45096
A76: TXN_1900620 | B76: Smoothie | C76: 2 | D76: 4 | E76: 8 | F76: Credit Card | H76: 45274
A77: TXN_6420335 | B77: Coffee | C77: 1 | D77: 2 | E77: 2 | F77: Cash | G77: Takeaway | H77: 45123
A78: TXN_3858209 | B78: Sandwich | C78: 4 | D78: 4 | E78: 16 | F78: Cash | H78: 44979
A79: TXN_2091733 | B79: Salad | C79: 1 | D79: 5 | E79: 5 | G79: In-store
A80: TXN_8735480 | B80: Tea | C80: 5 | D80: 1.5 | E80: 7.5 | F80: Cash | H80: 45079
A81: TXN_3829165 | B81: Juice | C81: 4 | D81: 3 | E81: 12 | F81: Cash | G81: In-store | H81: 45092
A82: TXN_3748616 | B82: Coffee | C82: 2 | D82: 2 | E82: 4 | F82: Credit Card | G82: In-store | H82: 45269
A83: TXN_1993289 | B83: Sandwich | C83: 2 | D83: 4 | E83: 8 | G83: In-store | H83: 45034
A84: TXN_2123367 | B84: Cookie | C84: 2 | D84: 1 | E84: 2 | H84: 45237
A85: TXN_5266394 | B85: Cake | C85: 3 | D85: 3 | E85: 9 | F85: Cash | G85: In-store | H85: 45227
A86: TXN_5107946 | B86: Cake | C86: 4 | D86: 3 | E86: 12 | F86: Credit Card | H86: 45282
A87: TXN_8035512 | B87: Tea | C87: 3 | D87: 1.5 | E87: 4.5 | F87: Cash | H87: 45228
A88: TXN_8718498 | B88: Cake | C88: 5 | D88: 3 | E88: 15 | F88: Credit Card | H88: 45046
A89: TXN_3955361 | B89: Cookie | C89: 5 | D89: 1 | E89: 5 | G89: Takeaway | H89: 45018
A90: TXN_9487821 | C90: 1 | D90: 5 | E90: 5 | F90: Digital Wallet | G90: Takeaway | H90: 45070
A91: TXN_4132730 | C91: 5 | D91: 1 | E91: 5 | G91: In-store | H91: 44997
A92: TXN_8976658 | B92: Tea | C92: 2 | D92: 1.5 | E92: 3 | F92: Credit Card | G92: In-store | H92: 45154
A93: TXN_5455936 | C93: 5 | D93: 3 | E93: 15 | G93: In-store | H93: 45227
A94: TXN_2725602 | B94: Juice | C94: 5 | D94: 3 | E94: 15 | F94: Credit Card | H94: 45179
A95: TXN_3011323 | B95: Coffee | C95: 3 | D95: 2 | E95: 6 | F95: Credit Card | H95: 44992
A96: TXN_6289610 | B96: Juice | C96: 3 | D96: 3 | E96: 9 | F96: Cash | G96: Takeaway | H96: 45145
A97: TXN_8268061 | B97: Salad | C97: 3 | D97: 5 | E97: 15 | G97: Takeaway | H97: 45158
A98: TXN_5220895 | B98: Salad | C98: 5 | D98: 5 | E98: 25 | F98: Cash | G98: In-store | H98: 45087
A99: TXN_3085509 | B99: Coffee | C99: 4 | D99: 2 | E99: 8 | F99: Digital Wallet | G99: In-store | H99: 45031
A100: TXN_9999113 | B100: Juice | C100: 4 | D100: 3 | E100: 12 | F100: Cash | G100: Takeaway | H100: 45073
...

Sheet Analysis
A1: Cafe Sales Analysis
A3: Metric | B3: Value
A4: Total Revenue | B4: =SUM(Data!E:E) -> 89096
A5: Total Quantity Sold | B5: =SUM(Data!C:C) -> 30180
A6: Number of Transactions | B6: =COUNTA(Data!A:A)-1 -> 10000
A7: Average Transaction Value | B7: =AVERAGE(Data!E:E) -> 8.9301393
A8: Maximum Transaction Value | B8: =MAX(Data!E:E) -> 25
A9: Minimum Transaction Value | B9: =MIN(Data!E:E) -> 1
A11: Revenue by Item
A12: Item | B12: Revenue
A13: {=_xlfn.UNIQUE(_xlfn._xlws.FILTER(Data!B2:B10001,Data!B2:B10001<>""))} -> Coffee | B13: =SUMIF(Data!B:B,A13,Data!E:E) -> 7072
A14: Cake | B14: =SUMIF(Data!B:B,A14,Data!E:E) -> 10404
A15: Cookie | B15: =SUMIF(Data!B:B,A15,Data!E:E) -> 3232
A16: Salad | B16: =SUMIF(Data!B:B,A16,Data!E:E) -> 17345
A17: Smoothie | B17: =SUMIF(Data!B:B,A17,Data!E:E) -> 13344
A18: Sandwich | B18: =SUMIF(Data!B:B,A18,Data!E:E) -> 13716
A19: Juice | B19: =SUMIF(Data!B:B,A19,Data!E:E) -> 10515
A20: Tea | B20: =SUMIF(Data!B:B,A20,Data!E:E) -> 4960.5
A23: Transaction Count by Item
A24: Item | B24: Transactions
A25: {=_xlfn.UNIQUE(_xlfn._xlws.FILTER(Data!B2:B10001,Data!B2:B10001<>""))} -> Coffee | B25: =COUNTIF(Data!B:B,A25) -> 1165
A26: Cake | B26: =COUNTIF(Data!B:B,A26) -> 1139
A27: Cookie | B27: =COUNTIF(Data!B:B,A27) -> 1092
A28: Salad | B28: =COUNTIF(Data!B:B,A28) -> 1148
A29: Smoothie | B29: =COUNTIF(Data!B:B,A29) -> 1096
A30: Sandwich | B30: =COUNTIF(Data!B:B,A30) -> 1131
A31: Juice | B31: =COUNTIF(Data!B:B,A31) -> 1171
A32: Tea | B32: =COUNTIF(Data!B:B,A32) -> 1089
A36: Average Revenue per Transaction
A37: Item | B37: Avg Revenue / Transaction
A38: {=_xlfn.UNIQUE(_xlfn._xlws.FILTER(Data!B2:B10001,Data!B2:B10001<>""))} -> Coffee | B38: =AVERAGEIF(Data!B:B,A38,Data!E:E) -> 6.0965517
A39: Cake | B39: =AVERAGEIF(Data!B:B,A39,Data!E:E) -> 9.142355
A40: Cookie | B40: =AVERAGEIF(Data!B:B,A40,Data!E:E) -> 2.9651376
A41: Salad | B41: =AVERAGEIF(Data!B:B,A41,Data!E:E) -> 15.135253
A42: Smoothie | B42: =AVERAGEIF(Data!B:B,A42,Data!E:E) -> 12.197441
A43: Sandwich | B43: =AVERAGEIF(Data!B:B,A43,Data!E:E) -> 12.170364
A44: Juice | B44: =AVERAGEIF(Data!B:B,A44,Data!E:E) -> 9.0025685
A45: Tea | B45: =AVERAGEIF(Data!B:B,A45,Data!E:E) -> 4.5592831

Sheet Pivot Tables
A1: Item | B1: Revenue | D1: Payment Method | E1: Revenue
A2: Cake | B2: 10404 | D2: Cash | E2: 20402.5
A3: Coffee | B3: 7072 | D3: Credit Card | E3: 20466
A4: Cookie | B4: 3232 | D4: Digital Wallet | E4: 20414
A5: Juice | B5: 10515 | D5: Grand Total | E5: 61282.5
A6: Salad | B6: 17345
A7: Sandwich | B7: 13716
A8: Smoothie | B8: 13344
A9: Tea | B9: 4960.5
A10: Grand Total | B10: 80588.5
A15: Location | B15: Revenue
A16: In-store | B16: 27174
A17: Takeaway | B17: 26552.5
A18: Grand Total | B18: 53726.5

Sheet Dashboard
A1: Cafe Sales Dashboard
A3: Total Revenue | D3: Total Quantity Sold | G3: Number of Transactions | K3: Average Transaction Value
A4: =Analysis!B4 -> 89096 | D4: =Analysis!B5 -> 30180 | G4: =Analysis!B6 -> 10000 | K4: =Analysis!B7 -> 8.9301393
A38: Key Insights
A39: • Salad generated the highest revenue among all items (17,345).
A40: • Credit Card generated the highest revenue among recorded payment methods (20,466).
A41: • In-store sales generated slightly higher revenue than Takeaway sales (27,174 vs 26,552.50).
A42: • Juice had the highest number of transactions (1,171), indicating strong customer demand by purchase frequency.
A43: • Salad generated the highest revenue, while Juice had the highest transaction count, showing that the most frequently purchased item was not the highest-revenue item.
